AUTHORS
LICENSE
MANIFEST.in
README.rst
setup.py
actistream/__init__.py
actistream/adapter.py
actistream/admin.py
actistream/apps.py
actistream/models.py
actistream/types.py
actistream/utils.py
actistream/migrations/0001_initial.py
actistream/migrations/0002_notice_index_together.py
actistream/migrations/0003_rename_notice_user_read_at_notice.py
actistream/migrations/__init__.py
actistream/templatetags/__init__.py
actistream/templatetags/actistream.py
actistream/tests/__init__.py
actistream/tests/activities.py
actistream/tests/models.py
actistream/tests/settings.py
actistream/tests/test_models.py
actistream/tests/templates/tests/activities/commentposted_message.html
actistream/tests/templates/tests/activities/commentposted_subject.txt
django_actistream.egg-info/PKG-INFO
django_actistream.egg-info/SOURCES.txt
django_actistream.egg-info/dependency_links.txt
django_actistream.egg-info/not-zip-safe
django_actistream.egg-info/requires.txt
django_actistream.egg-info/top_level.txt