Metadata-Version: 2.1
Name: django-actistream
Version: 3.0.2
Summary: Activities & notifications for Django
Home-page: http://github.com/pennersr/django-actistream
Author: Raymond Penners
Author-email: raymond.penners@intenct.nl
Project-URL: Changelog, https://github.com/pennersr/django-actistream/blob/main/ChangeLog.rst
Project-URL: Source, http://github.com/pennersr/django-actistream
Project-URL: Tracker, https://github.com/pennersr/django-actistream/issues
Project-URL: Donate, https://github.com/sponsors/pennersr
Platform: any
Classifier: Development Status :: 5 - Production/Stable
Classifier: Environment :: Web Environment
Classifier: Framework :: Django
Classifier: Intended Audience :: Developers
Classifier: License :: OSI Approved :: BSD License
Classifier: Operating System :: OS Independent
Classifier: Programming Language :: Python
Classifier: Programming Language :: Python :: 3.8
Classifier: Programming Language :: Python :: 3.9
Classifier: Programming Language :: Python :: 3.10
Classifier: Programming Language :: Python :: 3.11
Classifier: Topic :: Software Development :: Libraries :: Application Frameworks
Classifier: Topic :: Software Development :: Libraries :: Python Modules
License-File: LICENSE
License-File: AUTHORS
